fastreactpy/__init__.py
fastreactpy-0.0.3.dist-info/licenses/LICENSE
fastreactpy-0.0.3.dist-info/METADATA
fastreactpy-0.0.3.dist-info/WHEEL
fastreactpy-0.0.3.dist-info/top_level.txt
fastreactpy-0.0.3.dist-info/RECORD
