Metadata-Version: 2.4
Name: fastreactpy
Version: 0.0.3
Summary: Fast, lightweight reactive state for Python
Author-email: Malahim Haseeb <malahimhaseeb@gmail.com>
License-Expression: MIT
Keywords: reactive,state,python,reactivity,signals
Classifier: Development Status :: 3 - Alpha
Classifier: Intended Audience :: Developers
Classifier: Programming Language :: Python :: 3
Classifier: Programming Language :: Python :: 3.8
Classifier: Programming Language :: Python :: 3.9
Classifier: Programming Language :: Python :: 3.10
Classifier: Programming Language :: Python :: 3.11
Classifier: Programming Language :: Python :: 3.12
Requires-Python: >=3.8
License-File: LICENSE
Dynamic: license-file
